{"raceTitle": "Ballot Measures - Statewide Results", "Reporting": "80.8% (20,048 of 24,811) precincts reporting", "ReportingTime": "November 6, 2024, 2:32 a.m.", "ballot-measures": [{"Name": "Bonds for Public School and College Facilities", "Number": "02", "yesVotes": "5142914", "yesPercent": "56.8", "noVotes": "3912626", "noPercent": "43.2"}, {"Name": "Constitutional Right to Marriage", "Number": "03", "yesVotes": "5576489", "yesPercent": "61.3", "noVotes": "3515976", "noPercent": "38.7"}, {"Name": "Bonds for Water, Wildfire, and Climate Risks", "Number": "04", "yesVotes": "5277162", "yesPercent": "57.9", "noVotes": "3836718", "noPercent": "42.1"}, {"Name": "Bonds for Affordable Housing and Infrastructure", "Number": "05", "yesVotes": "3938270", "yesPercent": "43.6", "noVotes": "5085103", "noPercent": "56.4"}, {"Name": "Eliminates Forcing Inmates to Work", "Number": "06", "yesVotes": "4014526", "yesPercent": "45.2", "noVotes": "4873315", "noPercent": "54.8"}, {"Name": "Raises Minimum Wage", "Number": "32", "yesVotes": "4376329", "yesPercent": "48.0", "noVotes": "4742740", "noPercent": "52.0"}, {"Name": "Local Government Residential Rent Control", "Number": "33", "yesVotes": "3448784", "yesPercent": "38.3", "noVotes": "5567612", "noPercent": "61.7"}, {"Name": "Restricts Spending of Prescription Revenues", "Number": "34", "yesVotes": "4500262", "yesPercent": "51.4", "noVotes": "4253847", "noPercent": "48.6"}, {"Name": "Provides Permanent Funding for Medi-Cal", "Number": "35", "yesVotes": "6006148", "yesPercent": "66.8", "noVotes": "2980201", "noPercent": "33.2"}, {"Name": "Increased Sentencing for Certain Drug and Theft Crimes", "Number": "36", "yesVotes": "6387155", "yesPercent": "70.4", "noVotes": "2680141", "noPercent": "29.6"}]}