{"d": [{"__type": "MapData:#ORResultsWebService", "AreaNum": "Statewide Partisan", "AreaType": null, "BallotOrder": 1, "CandidateID": "300056389", "CountyID": "", "CountyName": "", "CurrentDateTime": null, "Delegates": "", "IsCountywide": false, "IsReported": false, "OfficeSeqNo": "115010008", "PartyCode": "DEM", "PartyName": "", "PrecinctName": null, "PrecinctsPartial": 0, "PrecinctsReporting": 40, "RaceID": 300037839, "RaceName": "Governor - Democrat", "RecountPercent": 0, "RecountVotes": 0, "StatePrecinctID": null, "TotalPrecincts": 1315, "VoteFor": 1, "Winner": false, "calcCandidate": "Forest (Fora) Alexander", "calcCandidatePercentage": 0.02721664053316701, "calcCandidateVotes": 12480}, {"__type": "MapData:#ORResultsWebService", "AreaNum": "Statewide Partisan", "AreaType": null, "BallotOrder": 2, "CandidateID": "300056391", "CountyID": "", "CountyName": "", "CurrentDateTime": null, "Delegates": "", "IsCountywide": false, "IsReported": false, "OfficeSeqNo": "115010008", "PartyCode": "DEM", "PartyName": "", "PrecinctName": null, "PrecinctsPartial": 0, "PrecinctsReporting": 40, "RaceID": 300037839, "RaceName": "Governor - Democrat", "RecountPercent": 0, "RecountVotes": 0, "StatePrecinctID": null, "TotalPrecincts": 1315, "VoteFor": 1, "Winner": false, "calcCandidate": "James Atkinson IV", "calcCandidatePercentage": 0.012797055019921795, "calcCandidateVotes": 5868}, {"__type": "MapData:#ORResultsWebService", "AreaNum": "Statewide Partisan", "AreaType": null, "BallotOrder": 3, "CandidateID": "300056401", "CountyID": "", "CountyName": "", "CurrentDateTime": null, "Delegates": "", "IsCountywide": false, "IsReported": false, "OfficeSeqNo": "115010008", "PartyCode": "DEM", "PartyName": "", "PrecinctName": null, "PrecinctsPartial": 0, "PrecinctsReporting": 40, "RaceID": 300037839, "RaceName": "Governor - Democrat", "RecountPercent": 0, "RecountVotes": 0, "StatePrecinctID": null, "TotalPrecincts": 1315, "VoteFor": 1, "Winner": false, "calcCandidate": "Cal Kishawi", "calcCandidatePercentage": 0.005251415897745686, "calcCandidateVotes": 2408}, {"__type": "MapData:#ORResultsWebService", "AreaNum": "Statewide Partisan", "AreaType": null, "BallotOrder": 4, "CandidateID": "300056402", "CountyID": "", "CountyName": "", "CurrentDateTime": null, "Delegates": "", "IsCountywide": false, "IsReported": false, "OfficeSeqNo": "115010008", "PartyCode": "DEM", "PartyName": "", "PrecinctName": null, "PrecinctsPartial": 0, "PrecinctsReporting": 40, "RaceID": 300037839, "RaceName": "Governor - Democrat", "RecountPercent": 0, "RecountVotes": 0, "StatePrecinctID": null, "TotalPrecincts": 1315, "VoteFor": 1, "Winner": false, "calcCandidate": "Tina Kotek", "calcCandidatePercentage": 0.8362443653048897, "calcCandidateVotes": 383454}, {"__type": "MapData:#ORResultsWebService", "AreaNum": "Statewide Partisan", "AreaType": null, "BallotOrder": 5, "CandidateID": "300056398", "CountyID": "", "CountyName": "", "CurrentDateTime": null, "Delegates": "", "IsCountywide": false, "IsReported": false, "OfficeSeqNo": "115010008", "PartyCode": "DEM", "PartyName": "", "PrecinctName": null, "PrecinctsPartial": 0, "PrecinctsReporting": 40, "RaceID": 300037839, "RaceName": "Governor - Democrat", "RecountPercent": 0, "RecountVotes": 0, "StatePrecinctID": null, "TotalPrecincts": 1315, "VoteFor": 1, "Winner": false, "calcCandidate": "Donnie M Beckwith", "calcCandidatePercentage": 0.0038993071533095043, "calcCandidateVotes": 1788}, {"__type": "MapData:#ORResultsWebService", "AreaNum": "Statewide Partisan", "AreaType": null, "BallotOrder": 6, "CandidateID": "300056399", "CountyID": "", "CountyName": "", "CurrentDateTime": null, "Delegates": "", "IsCountywide": false, "IsReported": false, "OfficeSeqNo": "115010008", "PartyCode": "DEM", "PartyName": "", "PrecinctName": null, "PrecinctsPartial": 0, "PrecinctsReporting": 40, "RaceID": 300037839, "RaceName": "Governor - Democrat", "RecountPercent": 0, "RecountVotes": 0, "StatePrecinctID": null, "TotalPrecincts": 1315, "VoteFor": 1, "Winner": false, "calcCandidate": "David W Beem", "calcCandidatePercentage": 0.010529001642157879, "calcCandidateVotes": 4828}, {"__type": "MapData:#ORResultsWebService", "AreaNum": "Statewide Partisan", "AreaType": null, "BallotOrder": 7, "CandidateID": "300056403", "CountyID": "", "CountyName": "", "CurrentDateTime": null, "Delegates": "", "IsCountywide": false, "IsReported": false, "OfficeSeqNo": "115010008", "PartyCode": "DEM", "PartyName": "", "PrecinctName": null, "PrecinctsPartial": 0, "PrecinctsReporting": 40, "RaceID": 300037839, "RaceName": "Governor - Democrat", "RecountPercent": 0, "RecountVotes": 0, "StatePrecinctID": null, "TotalPrecincts": 1315, "VoteFor": 1, "Winner": false, "calcCandidate": "Steve William Laible", "calcCandidatePercentage": 0.007973079951062386, "calcCandidateVotes": 3656}, {"__type": "MapData:#ORResultsWebService", "AreaNum": "Statewide Partisan", "AreaType": null, "BallotOrder": 8, "CandidateID": "300056400", "CountyID": "", "CountyName": "", "CurrentDateTime": null, "Delegates": "", "IsCountywide": false, "IsReported": false, "OfficeSeqNo": "115010008", "PartyCode": "DEM", "PartyName": "", "PrecinctName": null, "PrecinctsPartial": 0, "PrecinctsReporting": 40, "RaceID": 300037839, "RaceName": "Governor - Democrat", "RecountPercent": 0, "RecountVotes": 0, "StatePrecinctID": null, "TotalPrecincts": 1315, "VoteFor": 1, "Winner": false, "calcCandidate": "Brittany Jones", "calcCandidatePercentage": 0.030023356588149856, "calcCandidateVotes": 13767}, {"__type": "MapData:#ORResultsWebService", "AreaNum": "Statewide Partisan", "AreaType": null, "BallotOrder": 9, "CandidateID": "300056404", "CountyID": "", "CountyName": "", "CurrentDateTime": null, "Delegates": "", "IsCountywide": false, "IsReported": false, "OfficeSeqNo": "115010008", "PartyCode": "DEM", "PartyName": "", "PrecinctName": null, "PrecinctsPartial": 0, "PrecinctsReporting": 40, "RaceID": 300037839, "RaceName": "Governor - Democrat", "RecountPercent": 0, "RecountVotes": 0, "StatePrecinctID": null, "TotalPrecincts": 1315, "VoteFor": 1, "Winner": false, "calcCandidate": "Tristan Sheppard", "calcCandidatePercentage": 0.012999871331587223, "calcCandidateVotes": 5961}, {"__type": "MapData:#ORResultsWebService", "AreaNum": "Statewide Partisan", "AreaType": null, "BallotOrder": 10, "CandidateID": "300058053", "CountyID": "", "CountyName": "", "CurrentDateTime": null, "Delegates": "", "IsCountywide": false, "IsReported": false, "OfficeSeqNo": "115010008", "PartyCode": "DEM", "PartyName": "", "PrecinctName": null, "PrecinctsPartial": 0, "PrecinctsReporting": 40, "RaceID": 300037839, "RaceName": "Governor - Democrat", "RecountPercent": 0, "RecountVotes": 0, "StatePrecinctID": null, "TotalPrecincts": 1315, "VoteFor": 1, "Winner": false, "calcCandidate": "Miranda Weigler", "calcCandidatePercentage": 0.021936873968199273, "calcCandidateVotes": 10059}]}